E030/Connect.py
E030/ETABS.py
E030/__init__.py
E030-1.1.6.dist-info/METADATA
E030-1.1.6.dist-info/WHEEL
E030-1.1.6.dist-info/top_level.txt
E030-1.1.6.dist-info/RECORD
