Metadata-Version: 2.1
Name: E030
Version: 1.1.6
Summary: Librería para el Análisis Sísmico según NTE E.030 de Perú
Home-page: https://ceint.institute/
Author: Alex Henrry Palomino Encinas
Author-email: sagep_peru@hotmail.com
License: MIT
Platform: UNKNOWN
Requires-Dist: pandas
Requires-Dist: numpy
Requires-Dist: matplotlib
Requires-Dist: plotly
Requires-Dist: comtypes
